{
	"$schema": "https://biomejs.dev/schemas/1.8.3/schema.json",
	"organizeImports": {
		"enabled": true
	},
	"linter": {
		"enabled": true,
		"rules": {
			"recommended": true
		},
		"ignore": [
			".env",
			"node_modules"
		]
	},
	"formatter": {
		"enabled": true,
		"formatWithErrors": false,
		"ignore": [
			"node_modules"
		],
		"attributePosition": "auto",
		"indentStyle": "space",
		"indentWidth": 2,
		"lineWidth": 80,
		"lineEnding": "lf"
	},
	"javascript": {
		"formatter": {
			"arrowParentheses": "always",
			"bracketSameLine": false,
			"bracketSpacing": true,
			"jsxQuoteStyle": "single",
			"quoteStyle": "single",
			"semicolons": "asNeeded",
			"trailingCommas": "none"
		}
	},
	"json": {
		"formatter": {
			"trailingCommas": "none"
		}
	}
}